caliperreader/__init__.py
caliperreader/caliperreader.py
caliperreader/caliperstreamreader.py
caliperreader/metadatadb.py
caliperreader/readererror.py
caliperreader/version.py
caliper_reader-0.4.1.dist-info/LICENSE
caliper_reader-0.4.1.dist-info/METADATA
caliper_reader-0.4.1.dist-info/WHEEL
caliper_reader-0.4.1.dist-info/top_level.txt
caliper_reader-0.4.1.dist-info/RECORD
