Metadata-Version: 2.1
Name: caliper-reader
Version: 0.4.1
Summary: A Python library for reading Caliper .cali files
Author-email: David Boehme <boehme3@llnl.gov>
License: Copyright (c) 2015-2021, Lawrence Livermore National Security, LLC.
Project-URL: Homepage, https://github.com/LLNL/Caliper
Classifier: Programming Language :: Python :: 3
Classifier: Development Status :: 5 - Production/Stable
Classifier: License :: OSI Approved :: BSD License
Classifier: Operating System :: OS Independent
Requires-Python: >=3.6
License-File: LICENSE
